collective.feedback-1.2.0-py3.11-nspkg.pth
collective/feedback/__init__.py
collective/feedback/configure.zcml
collective/feedback/interfaces.py
collective/feedback/permissions.zcml
collective/feedback/setuphandlers.py
collective/feedback/testing.py
collective/feedback/upgrades.py
collective/feedback/upgrades.zcml
collective/feedback/controlpanels/__init__.py
collective/feedback/controlpanels/configure.zcml
collective/feedback/controlpanels/settings.py
collective/feedback/locales/README.rst
collective/feedback/locales/__init__.py
collective/feedback/locales/collective.feedback.pot
collective/feedback/locales/update.py
collective/feedback/locales/update.sh
collective/feedback/locales/en/LC_MESSAGES/collective.feedback.po
collective/feedback/locales/it/LC_MESSAGES/collective.feedback.po
collective/feedback/profiles/default/actions.xml
collective/feedback/profiles/default/browserlayer.xml
collective/feedback/profiles/default/controlpanel.xml
collective/feedback/profiles/default/metadata.xml
collective/feedback/profiles/default/rolemap.xml
collective/feedback/profiles/default/registry/main.xml
collective/feedback/profiles/default/to_1100/rolemap.xml
collective/feedback/profiles/uninstall/browserlayer.xml
collective/feedback/restapi/__init__.py
collective/feedback/restapi/configure.zcml
collective/feedback/restapi/services/__init__.py
collective/feedback/restapi/services/add.py
collective/feedback/restapi/services/configure.zcml
collective/feedback/restapi/services/controlpanels.py
collective/feedback/restapi/services/delete.py
collective/feedback/restapi/services/get.py
collective/feedback/restapi/services/list_update.py
collective/feedback/restapi/services/update.py
collective/feedback/storage/__init__.py
collective/feedback/storage/catalog.py
collective/feedback/storage/configure.zcml
collective/feedback/storage/store.py
collective/feedback/tests/__init__.py
collective/feedback/tests/test_delete_content.py
collective/feedback/tests/test_feedbacks_add.py
collective.feedback-1.2.0.dist-info/LICENSE.GPL
collective.feedback-1.2.0.dist-info/LICENSE.rst
collective.feedback-1.2.0.dist-info/METADATA
collective.feedback-1.2.0.dist-info/WHEEL
collective.feedback-1.2.0.dist-info/entry_points.txt
collective.feedback-1.2.0.dist-info/namespace_packages.txt
collective.feedback-1.2.0.dist-info/top_level.txt
collective.feedback-1.2.0.dist-info/RECORD
