Metadata-Version: 2.1
Name: collective.feedback
Version: 1.2.0
Summary: Feedback mechanism integration for io-comune
Home-page: https://github.com/collective/collective.feedback
Author: RedTurtle Technology
Author-email: sviluppoplone@redturtle.it
License: GPL version 2
Project-URL: PyPI, https://pypi.org/project/collective.feedback/
Project-URL: Source, https://github.com/collective/collective.feedback
Project-URL: Tracker, https://github.com/collective/collective.feedback/issues
Keywords: Python Plone CMS
Classifier: Development Status :: 1 - Planning
Classifier: Environment :: Web Environment
Classifier: Framework :: Plone
Classifier: Framework :: Plone :: Addon
Classifier: Framework :: Plone :: 5.2
Classifier: Framework :: Plone :: 6.0
Classifier: Programming Language :: Python
Classifier: Programming Language :: Python :: 3.7
Classifier: Programming Language :: Python :: 3.8
Classifier: Programming Language :: Python :: 3.9
Classifier: Operating System :: OS Independent
Classifier: License :: OSI Approved :: GNU General Public License v2 (GPLv2)
Requires-Python: >=3.7
License-File: LICENSE.GPL
License-File: LICENSE.rst
Requires-Dist: setuptools
Requires-Dist: souper.plone
Requires-Dist: collective.honeypot >=2.1
Provides-Extra: test
Requires-Dist: gocept.pytestlayer ; extra == 'test'
Requires-Dist: plone.app.testing ; extra == 'test'
Requires-Dist: plone.restapi[test] ; extra == 'test'
Requires-Dist: pytest-cov ; extra == 'test'
Requires-Dist: pytest-plone >=0.2.0 ; extra == 'test'
Requires-Dist: pytest-docker ; extra == 'test'
Requires-Dist: pytest-mock ; extra == 'test'
Requires-Dist: pytest ; extra == 'test'
Requires-Dist: zest.releaser[recommended] ; extra == 'test'
Requires-Dist: zestreleaser.towncrier ; extra == 'test'
Requires-Dist: requests-mock ; extra == 'test'
